setup.py
py_block_diagram/__init__.py
py_block_diagram/digcomp.py
py_block_diagram.egg-info/PKG-INFO
py_block_diagram.egg-info/SOURCES.txt
py_block_diagram.egg-info/dependency_links.txt
py_block_diagram.egg-info/requires.txt
py_block_diagram.egg-info/top_level.txt