Metadata-Version: 2.1
Name: py_block_diagram
Version: 1.6.2
Summary: package for  the backend of modeling controls block diagrams in python
Home-page: https://github.com/ryanGT/py_block_diagram
Author: Ryan Krauss
Author-email: ryanwkrauss@gmail.com
Classifier: Programming Language :: Python :: 3
Classifier: License :: OSI Approved :: MIT License
Classifier: Operating System :: OS Independent
Requires-Dist: control
Requires-Dist: digcomp
Requires-Dist: krauss_misc
